npeuclid.py
npeuclid/__init__.py
npeuclid/npeuclid.py
npeuclid-0.1.2.dist-info/LICENSE.md
npeuclid-0.1.2.dist-info/METADATA
npeuclid-0.1.2.dist-info/WHEEL
npeuclid-0.1.2.dist-info/top_level.txt
npeuclid-0.1.2.dist-info/RECORD
